nonebot_plugin_github_webhook/__init__.py
nonebot_plugin_github_webhook/config.py
nonebot_plugin_github_webhook-0.0.0.dist-info/LICENSE
nonebot_plugin_github_webhook-0.0.0.dist-info/METADATA
nonebot_plugin_github_webhook-0.0.0.dist-info/WHEEL
nonebot_plugin_github_webhook-0.0.0.dist-info/RECORD
