Metadata-Version: 2.3
Name: nonebot-plugin-github-webhook
Version: 0.0.0
Summary: 一个用于接收 GitHub Webhook 并通过 OneBot 协议将推送通知转发到 QQ 群的服务。Nonebot 插件版本。
License: Apache License
Keywords: nonebot,nonebot2,github,webhook,qqbot,nonebot-plugin,nonebot-plugin-github-webhook
Author: AptS-1547
Author-email: apts-1547@esaps.net
Maintainer: AptS-1547
Maintainer-email: apts-1547@esaps.net
Requires-Python: >=3.11,<4.0
Classifier: Development Status :: 1 - Planning
Classifier: Intended Audience :: Developers
Classifier: License :: OSI Approved :: Apache Software License
Classifier: Natural Language :: Chinese (Simplified)
Classifier: Programming Language :: Python :: 3.11
Requires-Dist: nonebot-adapter-onebot (>=2.4.6,<3.0.0)
Requires-Dist: nonebot2 (>=2.4.2,<3.0.0)
Project-URL: Homepage, https://github.com/AptS-1547/nonebot-plugin-github-webhook
Project-URL: Repository, https://github.com/AptS-1547/nonebot-plugin-github-webhook
Project-URL: changelog, https://github.com/AptS-1547/nonebot-plugin-github-webhook/releases
Project-URL: issue, https://github.com/AptS-1547/nonebot-plugin-github-webhook/issues
